{
  "fase": 9,
  "version": "1.1.0",
  "date": "2025-09-19T00:00:00Z",
  "goals": [
    "Correlation ID i alle REST-responser",
    "Unified error/success schema",
    "Rate limiting per API-nøkkel",
    "Logging av API-kall til JSONL",
    "Single-return struktur i REST callback",
    "Oppdatert manual og changelog"
  ],
  "verification": {
    "placeholder_scan": {
      "count": 0,
      "status": "ok"
    },
    "qa_summary_ref": "qa_summary.json",
    "overall_ok": true
  },
  "notes": "Fase 9 fullført uten forbudte mønstre."
}